[
    {
        "prettyUrl": "property-apartment-nsw-chatswood-436821788",
        "standard": false,
        "midtier": false,
        "lister": {
            "website": "http://www.rwayrealtychatswood.com",
            "phoneNumber": "0416416550",
            "name": "Henry Zhang",
            "mainPhoto": {
                "server": "https://i3.au.reastatic.net",
                "name": "main photo",
                "uri": "/781a871b59452f0320c9fbe2ed8782e1d773852e32d0b84f52a72eb28409dcd6/main.jpg"
            },
            "id": "3166904",
            "email": "h.zhang@raywhite.com"
        },
        "featured": false,
        "signature": true,
        "channel": "rent",
        "description": "Positioned on level 51 of Chatswood's iconic 'Metro Grand' with spectacular district views, this over sized north-east facing three bedroom apartment is sure to provide the ultimate lifestyle of luxury and sophistication. Its expansive open plan design, pristine finishes and bright and airy interiors provide a highly desirable home. In addition to its stunning internal features, the home includes two security car spaces and storage on title, as well as luxe building facilities including a swimming pool and gymnasium. Ready to move in and indulge, the apartment at an exclusive address, just footsteps to Chatswood Interchange, an abundance of local shops, cafes and restaurants.<br/><br/>- Expansive open floorplan with stunning district views<br/>- Floor to ceiling glass windows, superior quality fixtures and fittings<br/>- Gourmet stone crafted kitchen with quality Miele appliances<br/>- Five burner gas cooktop, large versatile bench top<br/>- Master suite with built in walk-in-robes and ensuite<br/>- Spacious 2nd and 3rd bedroom with built in robes, ducted a/c<br/>- Contemporary bathrooms, internal laundry room, plentiful storage<br/>- Double security car space, storage cage, intercom system, lift access<br/>- Iconic building with resort style facilities including swimming pool, spa, gym<br/>- Approx. 2 mins walk to Chatswood Interchange, shops and eateries<br/>- Approx. 5 mins walk to Chatswood Westfield shopping centre<br/><br/>Open Home Times: Please note that open times are subject to change. Please confirm on the day via our website https://rwayrealtychatswood.com/properties/for-rent/open-for-inspection",
        "advertising": {
            "region": "upper_north_shore",
            "priceRange": "1000pw_2000pw"
        },
        "showAgencyLogo": true,
        "title": "Indulge In Luxury Living, North-East Facing Three Bedroom Haven",
        "listers": [
            {
                "website": "http://www.rwayrealtychatswood.com",
                "phoneNumber": "0416416550",
                "name": "Henry Zhang",
                "mainPhoto": {
                    "server": "https://i3.au.reastatic.net",
                    "name": "main photo",
                    "uri": "/781a871b59452f0320c9fbe2ed8782e1d773852e32d0b84f52a72eb28409dcd6/main.jpg"
                },
                "id": "3166904",
                "email": "h.zhang@raywhite.com"
            }
        ],
        "features": {
            "general": { "bedrooms": 3, "bathrooms": 2, "parkingSpaces": 2 }
        },
        "price": { "display": "$1,950 Per Week" },
        "propertyType": "apartment",
        "productDepth": "signature",
        "calculator": {
            "brandingColors": { "text": "#e4002b", "primary": "#ffffff" },
            "subtitle": "Calculate repayments for this property",
            "title": "Buy or Rent Calculator"
        },
        "images": [
            {
                "server": "https://i3.au.reastatic.net",
                "name": "photo",
                "uri": "/5c86e22b7e73ff6b4bb70e8010c32601abbfe48aa2ebe0bf9cf6deb9d7d9f17f/image.jpg"
            },
            {
                "server": "https://i3.au.reastatic.net",
                "name": "photo",
                "uri": "/dc7f061d94a6752fbe8a94b509a14ccf06f90b6fa2cbac88766d5d45bde15201/image.jpg"
            },
            {
                "server": "https://i3.au.reastatic.net",
                "name": "photo",
                "uri": "/ec94b5437923da522888f1ecfad78d32613bf50a206ee27ec7c7478c45d34a75/image.jpg"
            },
            {
                "server": "https://i3.au.reastatic.net",
                "name": "photo",
                "uri": "/c3e6c9efcb09efd5fb1a3c275cab0f82b190f834b0850ba9858fe194fe39b3c4/image.jpg"
            },
            {
                "server": "https://i3.au.reastatic.net",
                "name": "photo",
                "uri": "/8a208d1eeccbca011d9a0efa515c618c71f9626939e51f97c357da40d1017b86/image.jpg"
            },
            {
                "server": "https://i3.au.reastatic.net",
                "name": "photo",
                "uri": "/ae6ad679fb2c3baa9db90cd8cd6c64ac3739a89615d0838c29d6cc26f5b542ba/image.jpg"
            },
            {
                "server": "https://i3.au.reastatic.net",
                "name": "photo",
                "uri": "/ef53b44156de486a4516b519bf6193b97cd15d27084f4b899d70d830d0d6b446/image.jpg"
            }
        ],
        "address": {
            "streetAddress": "5102/438 Victoria Ave",
            "locality": "Chatswood",
            "postcode": "2067",
            "suburb": "Chatswood",
            "location": { "latitude": -33.79729327, "longitude": 151.18065827 },
            "subdivisionCode": "NSW",
            "state": "NSW",
            "showAddress": true
        },
        "classicProject": false,
        "agency": {
            "website": "http://www.rwayrealtychatswood.com",
            "address": {
                "streetAddress": "SHOP 5, 28 Anderson Street",
                "postcode": "2067",
                "suburb": "Chatswood",
                "state": "NSW"
            },
            "phoneNumber": "02 9196 8788",
            "brandingColors": { "text": "#000000", "primary": "#ffe512" },
            "name": "Ray White AY Realty Chatswood",
            "logo": {
                "images": [
                    {
                        "server": "https://i3.au.reastatic.net",
                        "name": "large",
                        "uri": "/170x32/35cf0218ae06159ccac043664a51fd81578b2ff738f2c8037aa05ed10c14fac1/logo.jpg"
                    },
                    {
                        "server": "https://i3.au.reastatic.net",
                        "name": "default",
                        "uri": "/160x30/35cf0218ae06159ccac043664a51fd81578b2ff738f2c8037aa05ed10c14fac1/logo.jpg"
                    },
                    {
                        "server": "https://i3.au.reastatic.net",
                        "name": "small",
                        "uri": "/114x21/35cf0218ae06159ccac043664a51fd81578b2ff738f2c8037aa05ed10c14fac1/logo.jpg"
                    },
                    {
                        "server": "https://i3.au.reastatic.net",
                        "name": "hero image",
                        "uri": "/1536x800/e963c06b2eba22fd7149ff46ee2b035e837b14c077dd042eca8326783c6e456d/main.gif"
                    }
                ],
                "links": {
                    "small": "/114x21/35cf0218ae06159ccac043664a51fd81578b2ff738f2c8037aa05ed10c14fac1/logo.jpg",
                    "hero image": "/1536x800/e963c06b2eba22fd7149ff46ee2b035e837b14c077dd042eca8326783c6e456d/main.gif",
                    "default": "/160x30/35cf0218ae06159ccac043664a51fd81578b2ff738f2c8037aa05ed10c14fac1/logo.jpg",
                    "large": "/170x32/35cf0218ae06159ccac043664a51fd81578b2ff738f2c8037aa05ed10c14fac1/logo.jpg"
                }
            },
            "agencyId": "KYIWHA",
            "email": "ayrealtychatswood.nsw@raywhite.com"
        },
        "isSoldChannel": false,
        "isBuyChannel": false,
        "signatureProject": false,
        "agencyListingId": "R3083948",
        "propertyFeatures": [
            {
                "features": ["Carport: 2"],
                "section": "outdoor",
                "label": "Outdoor Features"
            }
        ],
        "listingId": "436821788",
        "bond": { "display": "$7,800", "value": 7800 },
        "mainImage": {
            "server": "https://i3.au.reastatic.net",
            "name": "main photo",
            "uri": "/ced2291a78e9009b4eaad4cf75e4504cb3ddeafa51504bbe0cf8818c3375af6b/image.jpg"
        },
        "dateAvailable": {
            "date": "09 Jun 2023",
            "dateDisplay": "09 Jun 2023"
        },
        "modifiedDate": { "value": "" },
        "inspectionsAndAuctions": [],
        "generalFeatures": {
            "bedrooms": {
                "label": "Bedrooms: 3",
                "type": "bedrooms",
                "value": 3
            },
            "bathrooms": {
                "label": "Bathrooms: 2",
                "type": "bathrooms",
                "value": 2
            },
            "parkingSpaces": {
                "label": "Parking Spaces: 2",
                "type": "parkingSpaces",
                "value": 2
            }
        },
        "isRentChannel": true,
        "applyOnline": false,
        "status": { "label": "New", "type": "new_listing" }
    },
    {
        "prettyUrl": "property-house-nsw-chatswood-436619460",
        "standard": false,
        "midtier": false,
        "lister": {
            "website": "http://www.shead.com.au",
            "phoneNumber": "0431500571",
            "name": "Jessie Tian",
            "mainPhoto": {
                "server": "https://i3.au.reastatic.net",
                "name": "main photo",
                "uri": "/99eeed51e05851d3dc28e2fb1b4703c346ad39883050d2cc70b0f87a82202e80/main.jpg"
            },
            "id": "3133756",
            "email": "jessie.tian@shead.com.au,5AR3RV34@mail.snug.com,capture@shead.agentboxmail.com.au"
        },
        "featured": false,
        "signature": true,
        "channel": "rent",
        "description": "A character home with new paint. This light and airy character filled home offers three spacious bedrooms, kitchen with gas cooking, floorboards in most rooms,<br/>spacious back yard and 1 x garage. Within walking distance to schools, shops and transport.<br/><br/>For more information, please contact Raymond Shao on 02 8448 1200,<br/>Email: raymond.shao@shead.com.au (Property Manager)<br/>-----------------------<br/>How to apply:<br/>Please note; You MUST view the property prior to submitting an application<br/>Step 1. Log on to https://www.realestate.com.au/<br/>Step 2. Navigate to the property you are applying for<br/>Step 3. Click \"Apply for this property\" and create a sign-up login on realestate.com.<br/>Step 4. Follow the steps and complete the online application<br/>Step 5. Upload all supporting documents, then submit.<br/><br/>SUPPORTING DOCUMENTS REQUIRED**<br/>Copy of current passport (Visa required if not Australian) & copy of driver's license<br/>Utility Bill, Payslip, & most recent bank statement<br/>Tenancy Ledger (rates notice/documentation showing ownership of property if home owner)<br/>",
        "showAgencyLogo": true,
        "title": "SPACIOUS AND CONVENIENT",
        "listers": [
            {
                "website": "http://www.shead.com.au",
                "phoneNumber": "0431500571",
                "name": "Jessie Tian",
                "mainPhoto": {
                    "server": "https://i3.au.reastatic.net",
                    "name": "main photo",
                    "uri": "/99eeed51e05851d3dc28e2fb1b4703c346ad39883050d2cc70b0f87a82202e80/main.jpg"
                },
                "id": "3133756",
                "email": "jessie.tian@shead.com.au,5AR3RV34@mail.snug.com,capture@shead.agentboxmail.com.au"
            },
            {
                "website": "http://www.shead.com.au",
                "phoneNumber": "0431500568",
                "name": "Raymond Shao",
                "mainPhoto": {
                    "server": "https://i3.au.reastatic.net",
                    "name": "main photo",
                    "uri": "/f59997f3951fe4a8bd5d59b662245fde8c24b5ed43653f8cbb188b08ff378779/main.jpg"
                },
                "id": "3171340",
                "email": "raymond.shao@shead.com.au,capture@shead.agentboxmail.com.au"
            }
        ],
        "features": {
            "general": { "bedrooms": 3, "bathrooms": 1, "parkingSpaces": 1 }
        },
        "price": { "display": "$950 per week" },
        "propertyType": "house",
        "productDepth": "signature",
        "calculator": {
            "brandingColors": { "text": "#e4002b", "primary": "#ffffff" },
            "subtitle": "Calculate repayments for this property",
            "title": "Buy or Rent Calculator"
        },
        "images": [
            {
                "server": "https://i3.au.reastatic.net",
                "name": "photo",
                "uri": "/13593bf078da3e9f41a4a9f77edeae58ab716799337d7146c217bc131d458e8b/image.jpg"
            },
            {
                "server": "https://i3.au.reastatic.net",
                "name": "photo",
                "uri": "/15312cfae4461c27002af42a2f6874d588f6666d63010b1dffd645967e99865e/image.jpg"
            },
            {
                "server": "https://i3.au.reastatic.net",
                "name": "photo",
                "uri": "/d4ef973bb44a0232d256feb3eeeeebe6413b67b7c9dfc03f98caf89159527f33/image.jpg"
            },
            {
                "server": "https://i3.au.reastatic.net",
                "name": "photo",
                "uri": "/5512e9943b8fcf7e4126b68de2ee2c33294a09781518ab6bafc22009392df656/image.jpg"
            }
        ],
        "address": {
            "streetAddress": "21 Centennial Avenue",
            "locality": "Chatswood",
            "postcode": "2067",
            "suburb": "Chatswood",
            "location": { "latitude": -33.79852962, "longitude": 151.17475221 },
            "subdivisionCode": "NSW",
            "state": "NSW",
            "showAddress": true
        },
        "classicProject": false,
        "agency": {
            "website": "http://www.shead.com.au",
            "address": {
                "streetAddress": "75 Archer Street",
                "postcode": "2067",
                "suburb": "Chatswood",
                "state": "NSW"
            },
            "phoneNumber": "02 8448 1200",
            "brandingColors": { "text": "#ffffff", "primary": "#00B5B0" },
            "name": "Shead Property - Chatswood",
            "logo": {
                "images": [
                    {
                        "server": "https://i3.au.reastatic.net",
                        "name": "large",
                        "uri": "/170x32/ca4530040aef6899b9eebc653dc491341b2248c4df54e84a1bf4224f6142c96c/logo.gif"
                    },
                    {
                        "server": "https://i3.au.reastatic.net",
                        "name": "default",
                        "uri": "/160x30/ca4530040aef6899b9eebc653dc491341b2248c4df54e84a1bf4224f6142c96c/logo.gif"
                    },
                    {
                        "server": "https://i3.au.reastatic.net",
                        "name": "small",
                        "uri": "/114x21/ca4530040aef6899b9eebc653dc491341b2248c4df54e84a1bf4224f6142c96c/logo.gif"
                    },
                    {
                        "server": "https://i3.au.reastatic.net",
                        "name": "hero image",
                        "uri": "/1536x800/f4622f71ef645dbd509eead9c42c1035da71a4105dc2ea82ce9667ce4e720b95/main.gif"
                    }
                ],
                "links": {
                    "small": "/114x21/ca4530040aef6899b9eebc653dc491341b2248c4df54e84a1bf4224f6142c96c/logo.gif",
                    "hero image": "/1536x800/f4622f71ef645dbd509eead9c42c1035da71a4105dc2ea82ce9667ce4e720b95/main.gif",
                    "default": "/160x30/ca4530040aef6899b9eebc653dc491341b2248c4df54e84a1bf4224f6142c96c/logo.gif",
                    "large": "/170x32/ca4530040aef6899b9eebc653dc491341b2248c4df54e84a1bf4224f6142c96c/logo.gif"
                }
            },
            "agencyId": "XFNCHA",
            "email": "realestate@shead.com.au"
        },
        "isSoldChannel": false,
        "isBuyChannel": false,
        "signatureProject": false,
        "agencyListingId": "1P17915",
        "propertyFeatures": [
            {
                "features": ["Garage: 1"],
                "section": "outdoor",
                "label": "Outdoor Features"
            }
        ],
        "listingId": "436619460",
        "mainImage": {
            "server": "https://i3.au.reastatic.net",
            "name": "main photo",
            "uri": "/56ee36262bf764f855a0a107922c5ff92f31b6b036a4c43c470ddd5643a04085/image.jpg"
        },
        "dateAvailable": {
            "date": "13 Apr 2023",
            "dateDisplay": "Available now"
        },
        "modifiedDate": { "value": "" },
        "inspectionsAndAuctions": [],
        "generalFeatures": {
            "bedrooms": {
                "label": "Bedrooms: 3",
                "type": "bedrooms",
                "value": 3
            },
            "bathrooms": {
                "label": "Bathrooms: 1",
                "type": "bathrooms",
                "value": 1
            },
            "parkingSpaces": {
                "label": "Parking Spaces: 1",
                "type": "parkingSpaces",
                "value": 1
            }
        },
        "isRentChannel": true,
        "applyOnline": false
    },
    {
        "prettyUrl": "property-apartment-nsw-chatswood-436529672",
        "standard": false,
        "midtier": false,
        "lister": {
            "website": "http://www.century21.com.au/chatswood",
            "phoneNumber": "0401003338",
            "name": "Jeremy Hong",
            "mainPhoto": {
                "server": "https://i3.au.reastatic.net",
                "name": "main photo",
                "uri": "/c826e1806f8e6e62dfc0a5370bc23138a62ebb5b9ff3f9b19324c731f62ee6b1/main.jpg"
            },
            "id": "1606698",
            "email": "leasing@c21seiwa.com.au"
        },
        "featured": false,
        "signature": true,
        "channel": "rent",
        "description": "Superb contemporary two bedroom executive apartment in the prestigious 'Altura' building conveniently located in the heart of Chatswood, featuring:-<br/>- New Carpet throughout.<br/>- Two large bedrooms with built-in robes<br/>- Two bathrooms (ensuite with bath)<br/>- Stone benchtop gas kitchen with stainless steel appliances including dishwasher<br/>- L-Shaped lounge and dining flowing out to extra large balcony<br/>- Internal Laundry with dryer<br/>- Reverse cycle air-conditioning throughout <br/>- Secure undercover parking<br/><br/>Complete with first class facilities only found in a Mirvac Quality development including Gym, 25 Metre outdoor pool, indoor pool, BBQ area.<br/><br/>CALL CENTURY 21 SEIWA TODAY TO INSPECT - 0401 003 338",
        "showAgencyLogo": true,
        "title": "Executive Mirvac Apartment ** Available Now **",
        "listers": [
            {
                "website": "http://www.century21.com.au/chatswood",
                "phoneNumber": "0401003338",
                "name": "Jeremy Hong",
                "mainPhoto": {
                    "server": "https://i3.au.reastatic.net",
                    "name": "main photo",
                    "uri": "/c826e1806f8e6e62dfc0a5370bc23138a62ebb5b9ff3f9b19324c731f62ee6b1/main.jpg"
                },
                "id": "1606698",
                "email": "leasing@c21seiwa.com.au"
            }
        ],
        "features": {
            "general": { "bedrooms": 2, "bathrooms": 2, "parkingSpaces": 1 }
        },
        "price": { "display": "$950 Per Week" },
        "propertyType": "apartment",
        "productDepth": "signature",
        "calculator": {
            "brandingColors": { "text": "#e4002b", "primary": "#ffffff" },
            "subtitle": "Calculate repayments for this property",
            "title": "Buy or Rent Calculator"
        },
        "images": [
            {
                "server": "https://i3.au.reastatic.net",
                "name": "photo",
                "uri": "/4386e46b28fdf3f801e48d1993381af5ac671aba219b7a2bb919b21429e51d97/image.jpg"
            },
            {
                "server": "https://i3.au.reastatic.net",
                "name": "photo",
                "uri": "/19e00513e282c8ecdd33fd9c69f42fd58a86750ccb817eeab6be6dbbbd74e734/image.jpg"
            },
            {
                "server": "https://i3.au.reastatic.net",
                "name": "photo",
                "uri": "/dbc0fb37060afa5c2f32ffcacae81edbc5b9c15d56ab99acd9237562027241fe/image.jpg"
            },
            {
                "server": "https://i3.au.reastatic.net",
                "name": "photo",
                "uri": "/8121cb2bec62a74ca81d4158074e7f86d708542f9b132185337e780d79c1e933/image.jpg"
            },
            {
                "server": "https://i3.au.reastatic.net",
                "name": "photo",
                "uri": "/a6cf559beef14e3d07562c7ca94ced9a411e03ad86301ab557264e0572d0230b/image.jpg"
            },
            {
                "server": "https://i3.au.reastatic.net",
                "name": "photo",
                "uri": "/0ae3f61d1b2e5b23f88861d6f5db80c8c9eec4bd770e24b4600b3151f88b5a3b/image.jpg"
            },
            {
                "server": "https://i3.au.reastatic.net",
                "name": "photo",
                "uri": "/f7e740a3b6ca81de644841bc7ccd46fc57c40682bc774db2ee177a346b46e166/image.jpg"
            },
            {
                "server": "https://i3.au.reastatic.net",
                "name": "photo",
                "uri": "/49d8a9b23397813486c94d7f85a02732823317489a4bcc20701898469c135d54/image.jpg"
            }
        ],
        "address": {
            "streetAddress": "505/11 Railway Street",
            "locality": "Chatswood",
            "postcode": "2067",
            "suburb": "Chatswood",
            "location": { "latitude": -33.79370019, "longitude": 151.18033089 },
            "subdivisionCode": "NSW",
            "state": "NSW",
            "showAddress": true
        },
        "classicProject": false,
        "agency": {
            "website": "http://www.century21.com.au/chatswood",
            "address": {
                "streetAddress": "Suite 1, 11 Railway Street",
                "postcode": "2067",
                "suburb": "Chatswood",
                "state": "NSW"
            },
            "phoneNumber": "02 9411 8044",
            "brandingColors": { "text": "#ffffff", "primary": "#252526" },
            "name": "Century 21 - Seiwa",
            "logo": {
                "images": [
                    {
                        "server": "https://i3.au.reastatic.net",
                        "name": "large",
                        "uri": "/170x32/1729626b45093386ea4e76923164c19a9410572e9e9eda7b19e04aaaa75ad538/logo.jpg"
                    },
                    {
                        "server": "https://i3.au.reastatic.net",
                        "name": "default",
                        "uri": "/160x30/1729626b45093386ea4e76923164c19a9410572e9e9eda7b19e04aaaa75ad538/logo.jpg"
                    },
                    {
                        "server": "https://i3.au.reastatic.net",
                        "name": "small",
                        "uri": "/114x21/1729626b45093386ea4e76923164c19a9410572e9e9eda7b19e04aaaa75ad538/logo.jpg"
                    },
                    {
                        "server": "https://i3.au.reastatic.net",
                        "name": "hero image",
                        "uri": "/1536x800/ce452c49ad2e2ffe1c9375261252c47256a340f4232fe838469e8956622fc47a/main.jpg"
                    }
                ],
                "links": {
                    "small": "/114x21/1729626b45093386ea4e76923164c19a9410572e9e9eda7b19e04aaaa75ad538/logo.jpg",
                    "hero image": "/1536x800/ce452c49ad2e2ffe1c9375261252c47256a340f4232fe838469e8956622fc47a/main.jpg",
                    "default": "/160x30/1729626b45093386ea4e76923164c19a9410572e9e9eda7b19e04aaaa75ad538/logo.jpg",
                    "large": "/170x32/1729626b45093386ea4e76923164c19a9410572e9e9eda7b19e04aaaa75ad538/logo.jpg"
                }
            },
            "agencyId": "THNCHA",
            "email": "garo@c21seiwa.com.au"
        },
        "isSoldChannel": false,
        "isBuyChannel": false,
        "signatureProject": false,
        "agencyListingId": "NSW107516471",
        "propertyFeatures": [
            {
                "features": ["Open Spaces: 1"],
                "section": "outdoor",
                "label": "Outdoor Features"
            },
            {
                "features": ["Air Conditioning"],
                "section": "indoor",
                "label": "Indoor Features"
            }
        ],
        "listingId": "436529672",
        "bond": { "display": "$3,800", "value": 3800 },
        "mainImage": {
            "server": "https://i3.au.reastatic.net",
            "name": "main photo",
            "uri": "/67ac61a2970fd18d7f455986853269d241b9a757c8fb52415bd1f0b96e3e1a9c/image.jpg"
        },
        "dateAvailable": {
            "date": "13 Apr 2023",
            "dateDisplay": "Available now"
        },
        "modifiedDate": { "value": "" },
        "inspectionsAndAuctions": [],
        "generalFeatures": {
            "bedrooms": {
                "label": "Bedrooms: 2",
                "type": "bedrooms",
                "value": 2
            },
            "bathrooms": {
                "label": "Bathrooms: 2",
                "type": "bathrooms",
                "value": 2
            },
            "parkingSpaces": {
                "label": "Parking Spaces: 1",
                "type": "parkingSpaces",
                "value": 1
            }
        },
        "isRentChannel": true,
        "applyOnline": false
    },
    {
        "prettyUrl": "property-apartment-nsw-chatswood-428783894",
        "standard": false,
        "midtier": false,
        "lister": {
            "phoneNumber": "0477004806",
            "name": "Centrium Chatswood",
            "mainPhoto": {
                "server": "https://i3.au.reastatic.net",
                "name": "main photo",
                "uri": "/64bf643fae6fa64bd07a9ed07fb89bffdb0f33e0993e8e8872306d47fa100edb/main.jpg"
            },
            "id": "2883406",
            "email": "centrium.leasing@meriton.com.au"
        },
        "featured": false,
        "signature": true,
        "channel": "rent",
        "description": "Luxurious Selection of 1 Bedroom Apartments - 1 available:<br/>at $700<br/><br/><br/>Luxurious High Rise Apartments | 9km from Sydney CBD | Onsite Childcare Centre & Retail Precinct | Close to Transport, Shopping Centres & Universities | Onsite Building Management | After Hours Security | Fully Equipped Gymnasium | Indoor Aquatic Centre with Heated Pool & Spa & Sauna | Spectacular Views<br/><br/>Uniquely designed and built to cater for an ultra-convenient lifestyle, Centrium brings to the market a mix of one, two and three bedroom apartments, just 9km from Sydney\u2019s CBD. Located in the beating heart of Chatswood, with an abundance of cafes, restaurants, shopping centres and cinema complexes, you will be spoilt for choice.<br/><br/>Boasting sweeping City, harbour and Central Sydney District views, some of the largest high rise apartments Chatswood has to offer and 5 star resort like facilities, you\u2019ll love living in Centrium, where convenience and luxe living come together in the skys.<br/><br/>When choosing to rent a Meriton Built For Rent apartment, you\u2019ll enjoy peace of minding knowing you have long term rental security, as Meriton retain a large portfolio of apartments. Meriton are continually investing in upgrades to our buildings, taking pride in ensuring buildings are kept to the highest of standards. <br/>Meriton is your sole point of contact and will take care of everything, from renewing leases to requesting maintenance. The ability to deal exclusively with Meriton, instead of multiple stakeholders like real estate agents, landlords or strata managers, ensures any issues that may arise are taken care of in a timely manner, without all the headaches!<br/><br/>APARTMENT FEATURES<br/><br/>\u2022 Lavish one bedroom apartments with built-ins, up to 63sqm internally<br/>\u2022 Balconies up to 8sqm with sweeping City, harbor and Central Sydney District views<br/>\u2022 A modern, open plan layout with free-flowing living areas<br/>\u2022 Many apartments include secure parking and storage with direct lift access<br/>\u2022 Stylish kitchens featuring caesarstone benchtops, duel sinks and ILVE stainless steel appliances including microwave, gas cook top and dishwasher<br/>\u2022 Sleek and spacious bathrooms featuring caesarstone countertop, frameless glass shower and floor to ceiling tiled walls<br/>\u2022 Internal laundry with dryer <br/>\u2022 Reverse cycle air-conditioning system <br/>\u2022 Security intercom system <br/><br/><br/>DEVELOPMENT FEATURES<br/><br/>\u2022 Spectacular Indoor aquatic centre including lap pool and spa<br/>\u2022 Fully-equipped fitness centre exclusive to residents<br/>\u2022 Onsite childcare centre and retail including a restaurant and cafe <br/>\u2022 Dedicated onsite building manager ensures all apartments and facilities are kept to a high standard. *Chinese speaking upon Requests <br/>\u2022 Comprehensive security including after hour security, intercom system, CCTV cameras and secure building access <br/>\u2022 Onsite maintenance team to ensure any necessary maintenance is attended to promptly<br/>\u2022 Onsite cleaning staff to maintain a high level of building cleanliness<br/>\u2022 Landscaped gardens<br/>\u2022 Bicycle parking available to all residents<br/><br/><br/><br/>LOCATION & LIFESTYLE<br/><br/>\u2022 9km from Sydney CBD<br/>\u2022 0.2km from Chatswood train station<br/>\u2022 Just a short walk to Chatswood Westfield, Chatswood Chase and Mandarin Centre<br/>\u2022 Easy access to Macquarie University and University of Technology Sydney<br/>\u2022 0.5km from Willoughby City Library<br/>\u2022 0.5km from Chatswood Oval<br/>\u2022 Less than 2km <br/><br/>CONTACT BUILDING MANAGEMENT ON 0477 004 806 TO ARRANGE YOUR PRIVATE INSPECTION TODAY!<br/><br/>Building Management Office located at 18 Thomas St, Chatswood<br/><br/>Mon-Fri 9am - 5pm<br/>Sat 9am \u2013 12:30pm<br/><br/>** Disclaimer: Meriton Group has made all reasonable attempts to verify the accuracy of the information provided but does not warrant or guarantee such accuracy. Photography and illustrations are indicative representations of features and finishes only. Any interested persons should rely on their own enquiries to verify the information provided, including those related to available utility and internet service providers as additional connection fees may apply.**",
        "showAgencyLogo": true,
        "title": "LUXURY APARTMENTS AVAILABLE IN CHATSWOOD!",
        "listers": [
            {
                "phoneNumber": "0477004806",
                "name": "Centrium Chatswood",
                "mainPhoto": {
                    "server": "https://i3.au.reastatic.net",
                    "name": "main photo",
                    "uri": "/64bf643fae6fa64bd07a9ed07fb89bffdb0f33e0993e8e8872306d47fa100edb/main.jpg"
                },
                "id": "2883406",
                "email": "centrium.leasing@meriton.com.au"
            }
        ],
        "features": {
            "general": { "bedrooms": 1, "bathrooms": 1, "parkingSpaces": 0 }
        },
        "price": { "display": "$700 per week" },
        "propertyType": "apartment",
        "productDepth": "signature",
        "calculator": {
            "brandingColors": { "text": "#e4002b", "primary": "#ffffff" },
            "subtitle": "Calculate repayments for this property",
            "title": "Buy or Rent Calculator"
        },
        "images": [
            {
                "server": "https://i3.au.reastatic.net",
                "name": "photo",
                "uri": "/d7cecca655e6efa3ac2f4e0e405e9d461430671bab00ca8c8948fce855cff3ea/image.jpg"
            },
            {
                "server": "https://i3.au.reastatic.net",
                "name": "photo",
                "uri": "/1a289a053be0e5bed887913a29730e0a9a238a6ad594174482577beb06fcd856/image.jpg"
            },
            {
                "server": "https://i3.au.reastatic.net",
                "name": "photo",
                "uri": "/ef890b290de116f59dba89695586f9069302cf1cf2f617bdfb09f9dd77b2aace/image.jpg"
            },
            {
                "server": "https://i3.au.reastatic.net",
                "name": "photo",
                "uri": "/feb1581fab9c01ed40cbfd83504ba5cc29148f245d31a754e7ed07ee45d689e3/image.jpg"
            },
            {
                "server": "https://i3.au.reastatic.net",
                "name": "photo",
                "uri": "/20e897cce6be3ab16f5ceb0a5f7ac4c218a77b72f7a630af2c27514368f6aa0b/image.jpg"
            },
            {
                "server": "https://i3.au.reastatic.net",
                "name": "photo",
                "uri": "/2146f4d4a68e316332f7d92ef523eaec72fb78eeff98778e5747ebddf43d59b2/image.jpg"
            },
            {
                "server": "https://i3.au.reastatic.net",
                "name": "photo",
                "uri": "/4da5b5df608e587dc38a1e26cb113d00a7ea44d420488a7f45d1cf1da92ad5b7/image.jpg"
            },
            {
                "server": "https://i3.au.reastatic.net",
                "name": "photo",
                "uri": "/38edead359f6975ab416e80a9c6b44e34fc8bb1fd0106a6a565773429c7d2024/image.jpg"
            },
            {
                "server": "https://i3.au.reastatic.net",
                "name": "photo",
                "uri": "/aba3851042c73f904bf569eea86d5962e5fbe27e231d4cd2db54649037fa0e18/image.jpg"
            },
            {
                "server": "https://i3.au.reastatic.net",
                "name": "photo",
                "uri": "/7beeb5a925f787857f876938087a4d983215ad1672a95f025e6d99bce36e0a40/image.jpg"
            },
            {
                "server": "https://i3.au.reastatic.net",
                "name": "photo",
                "uri": "/bfb795e3991c3ea298be236c82de83f127f06e7df1692344ec06614a870f5f02/image.jpg"
            },
            {
                "server": "https://i3.au.reastatic.net",
                "name": "photo",
                "uri": "/ce0c556f83ec6c965d2e19c0e38f8357f66205586cd59c3b3eb9444fc2036a1a/image.jpg"
            },
            {
                "server": "https://i3.au.reastatic.net",
                "name": "photo",
                "uri": "/38c24dadf2b85b52a3a15790650bfed39a9cd3aabca898ba038bcccf04458082/image.jpg"
            },
            {
                "server": "https://i3.au.reastatic.net",
                "name": "photo",
                "uri": "/c8504b109df1be392183a79714681f1154039b1b17c96a8937ee7be0be9e603a/image.jpg"
            },
            {
                "server": "https://i3.au.reastatic.net",
                "name": "photo",
                "uri": "/104c37a7e186f5fd3ce478b10c2dce2ec0fae023b710f04d0eb41e565906c9a2/image.jpg"
            },
            {
                "server": "https://i3.au.reastatic.net",
                "name": "photo",
                "uri": "/c0db4f7ecd001f6420ccf9296c497ff670e947bcdc996ef64e68fcebb763305d/image.jpg"
            },
            {
                "server": "https://i3.au.reastatic.net",
                "name": "photo",
                "uri": "/4863120d8e3ab45c6c1a3b2f84778349b5ce573445334565139a10322c54411a/image.jpg"
            },
            {
                "server": "https://i3.au.reastatic.net",
                "name": "photo",
                "uri": "/189204b55590aadb0e978cc20f28f80d617a7c9162b9f8fa3699b2b6228d4522/image.jpg"
            },
            {
                "server": "https://i3.au.reastatic.net",
                "name": "floorplan",
                "resize": true,
                "uri": "/9f410040e6a8eae14541ed9dd0c802dfd59e01fb285d57da69a2bf172289352f/image.jpg"
            }
        ],
        "address": {
            "streetAddress": "18 Thomas St",
            "locality": "Chatswood",
            "postcode": "2067",
            "suburb": "Chatswood",
            "location": { "latitude": -33.7984472, "longitude": 151.17967436 },
            "subdivisionCode": "NSW",
            "state": "NSW",
            "showAddress": true
        },
        "classicProject": false,
        "agency": {
            "address": {
                "streetAddress": "Level 11, 528 Kent Street",
                "postcode": "2000",
                "suburb": "Sydney",
                "state": "NSW"
            },
            "phoneNumber": "0292872888",
            "brandingColors": { "text": "#000000", "primary": "#F5D1B8" },
            "name": "Meriton Built For Rent - SYDNEY",
            "logo": {
                "images": [
                    {
                        "server": "https://i3.au.reastatic.net",
                        "name": "large",
                        "uri": "/170x32/ec70ab1e49aee61e121451149d2d43ec84b3440373787530ce17efe2c1aa4617/logo.jpg"
                    },
                    {
                        "server": "https://i3.au.reastatic.net",
                        "name": "default",
                        "uri": "/160x30/ec70ab1e49aee61e121451149d2d43ec84b3440373787530ce17efe2c1aa4617/logo.jpg"
                    },
                    {
                        "server": "https://i3.au.reastatic.net",
                        "name": "small",
                        "uri": "/114x21/ec70ab1e49aee61e121451149d2d43ec84b3440373787530ce17efe2c1aa4617/logo.jpg"
                    },
                    {
                        "server": "https://i3.au.reastatic.net",
                        "name": "hero image",
                        "uri": "/1536x800/44bff7249fd92e6d7d15ecaed8196c4afd3c5348f27c42942d722be1739f935c/main.jpg"
                    }
                ],
                "links": {
                    "small": "/114x21/ec70ab1e49aee61e121451149d2d43ec84b3440373787530ce17efe2c1aa4617/logo.jpg",
                    "hero image": "/1536x800/44bff7249fd92e6d7d15ecaed8196c4afd3c5348f27c42942d722be1739f935c/main.jpg",
                    "default": "/160x30/ec70ab1e49aee61e121451149d2d43ec84b3440373787530ce17efe2c1aa4617/logo.jpg",
                    "large": "/170x32/ec70ab1e49aee61e121451149d2d43ec84b3440373787530ce17efe2c1aa4617/logo.jpg"
                }
            },
            "agencyId": "DLNFGP",
            "email": "marketing@meriton.com.au"
        },
        "isSoldChannel": false,
        "isBuyChannel": false,
        "signatureProject": false,
        "agencyListingId": "2d4b8952-ab75-4633-9313-0431f35cdd32",
        "propertyFeatures": [
            {
                "features": [
                    "Balcony",
                    "Secure Parking",
                    "Swimming Pool - Inground"
                ],
                "section": "outdoor",
                "label": "Outdoor Features"
            },
            {
                "features": [
                    "Air Conditioning",
                    "Broadband Internet Available",
                    "Built-in Wardrobes",
                    "Dishwasher",
                    "Indoor Spa",
                    "Intercom",
                    "Toilets: 1"
                ],
                "section": "indoor",
                "label": "Indoor Features"
            }
        ],
        "listingId": "428783894",
        "bond": { "display": "$2,800", "value": 2800 },
        "mainImage": {
            "server": "https://i3.au.reastatic.net",
            "name": "main photo",
            "uri": "/6cc12586d4b107a852c20c952449a38b40342c1033fdd6f9a143de216b3efa86/image.jpg"
        },
        "dateAvailable": {
            "date": "04 May 2023",
            "dateDisplay": "Available now"
        },
        "modifiedDate": { "value": "" },
        "inspectionsAndAuctions": [],
        "generalFeatures": {
            "bedrooms": {
                "label": "Bedrooms: 1",
                "type": "bedrooms",
                "value": 1
            },
            "bathrooms": {
                "label": "Bathrooms: 1",
                "type": "bathrooms",
                "value": 1
            }
        },
        "isRentChannel": true,
        "applyOnline": false
    },
    {
        "prettyUrl": "property-apartment-nsw-chatswood-436716888",
        "standard": false,
        "midtier": false,
        "lister": {
            "website": "http://www.fnrr.com.au",
            "phoneNumber": "0410628699",
            "name": "Cindy Zhang",
            "mainPhoto": {
                "server": "https://i3.au.reastatic.net",
                "name": "main photo",
                "uri": "/a0cbff53859a5a9fdaa1774d6e84abef8a2d4c44eeaadfcf5b4f534ce2910120/main.jpg"
            },
            "id": "2985327",
            "email": "cindy@fnrr.com.au"
        },
        "featured": false,
        "signature": true,
        "channel": "rent",
        "description": "Great 2 bedroom Apartment-High Park Tower<br/><br/>This two (2) bedroom, (2) bathroom apartment is in a popular building only 300 metres to the train station. Open plan kitchen, combined living and internal laundry. This unit also has air conditioning and the building has a pool and gym plus one (1) car space.<br/><br/>The apartment is conveniently located close to Eat Street, and Chatswood transport infrastructure and a short stroll to Chatswood shops and Entertainment in the Concourse.<br/><br/>Features:<br/>- Nearly brand New Carpets<br/>- Nearly New Blinds<br/><br/>- Open plan living and dining flows to balcony<br/>- Air-conditioning<br/>- Indoor heated pool, spa, sauna and gym facilities<br/><br/>All information contained here is gathered from sources we believe to be reliable, however we are merely passing this on. We cannot guarantee its accuracy and any interested persons should rely on their own inquiry.",
        "showAgencyLogo": true,
        "title": "Located in the heart of CHATSWOOD - High Park Tower",
        "listers": [
            {
                "website": "http://www.fnrr.com.au",
                "phoneNumber": "0410628699",
                "name": "Cindy Zhang",
                "mainPhoto": {
                    "server": "https://i3.au.reastatic.net",
                    "name": "main photo",
                    "uri": "/a0cbff53859a5a9fdaa1774d6e84abef8a2d4c44eeaadfcf5b4f534ce2910120/main.jpg"
                },
                "id": "2985327",
                "email": "cindy@fnrr.com.au"
            },
            {
                "website": "http://www.fnrr.com.au",
                "phoneNumber": "(02) 9412 1288",
                "name": "First National Regency Realty",
                "mainPhoto": {
                    "server": "https://i3.au.reastatic.net",
                    "name": "main photo",
                    "uri": "/0b5d279b03adf012f24b39cb41cf3a3f60a81043475d10008fb453c85ad85974/main.jpg"
                },
                "id": "2113778",
                "email": "250793@agentleads.desktop.com.au"
            }
        ],
        "features": {
            "general": { "bedrooms": 2, "bathrooms": 2, "parkingSpaces": 1 }
        },
        "price": { "display": "DEPOSIT TAKEN" },
        "propertyType": "apartment",
        "productDepth": "signature",
        "calculator": {
            "brandingColors": { "text": "#e4002b", "primary": "#ffffff" },
            "subtitle": "Calculate repayments for this property",
            "title": "Buy or Rent Calculator"
        },
        "images": [
            {
                "server": "https://i3.au.reastatic.net",
                "name": "photo",
                "uri": "/0066ae697fedd25bc29174d3783a983afa39c4276930d95ed9485afb293286e0/image.jpg"
            },
            {
                "server": "https://i3.au.reastatic.net",
                "name": "photo",
                "uri": "/07bd97d44ff57e4e76f04c31180dd35a3e5d36d72838975ce2ce8e0486974c12/image.jpg"
            },
            {
                "server": "https://i3.au.reastatic.net",
                "name": "photo",
                "uri": "/a2b9a8e917c281c5bfda71e74b89f310743839fdb88edf3412b11204d1d1e78d/image.jpg"
            },
            {
                "server": "https://i3.au.reastatic.net",
                "name": "photo",
                "uri": "/5ea5eac4db778a6ec495bfb0639d598c9365b1127f68ee0f2d132a75d511460c/image.jpg"
            },
            {
                "server": "https://i3.au.reastatic.net",
                "name": "photo",
                "uri": "/74c5a5185fc3dcc6fe1a532732990c698e54dade86c0a8366c2db9a1ba92afb0/image.jpg"
            },
            {
                "server": "https://i3.au.reastatic.net",
                "name": "floorplan",
                "resize": true,
                "uri": "/fac43958be45875aa0943c58220fa345ca83e0a90df7537c9ab7b7a5f0db1c3c/image.jpg"
            }
        ],
        "address": {
            "streetAddress": "Level 7. 54/14 Brown Street",
            "locality": "Chatswood",
            "postcode": "2067",
            "suburb": "Chatswood",
            "location": { "latitude": -33.79656004, "longitude": 151.17842466 },
            "subdivisionCode": "NSW",
            "state": "NSW",
            "showAddress": true
        },
        "classicProject": false,
        "agency": {
            "website": "http://www.fnrr.com.au",
            "address": {
                "streetAddress": "Suite 308, 7 Railway Street",
                "postcode": "2067",
                "suburb": "Chatswood",
                "state": "NSW"
            },
            "phoneNumber": "(02) 9412 1288",
            "brandingColors": { "text": "#ffffff", "primary": "#00467f" },
            "name": "First National Real Estate - Chatswood",
            "logo": {
                "images": [
                    {
                        "server": "https://i3.au.reastatic.net",
                        "name": "large",
                        "uri": "/170x32/c1f8d2ad2b87aa2487dbb76d2605e0fa506b793048d6d4b516f25cbb4d9e0e3d/logo.gif"
                    },
                    {
                        "server": "https://i3.au.reastatic.net",
                        "name": "default",
                        "uri": "/160x30/c1f8d2ad2b87aa2487dbb76d2605e0fa506b793048d6d4b516f25cbb4d9e0e3d/logo.gif"
                    },
                    {
                        "server": "https://i3.au.reastatic.net",
                        "name": "small",
                        "uri": "/114x21/c1f8d2ad2b87aa2487dbb76d2605e0fa506b793048d6d4b516f25cbb4d9e0e3d/logo.gif"
                    },
                    {
                        "server": "https://i3.au.reastatic.net",
                        "name": "hero image",
                        "uri": "/1536x800/5d8f7629cd78dffb465331a999d35309e34ebeff34946315c9f83d3f8e4d9c36/main.gif"
                    }
                ],
                "links": {
                    "small": "/114x21/c1f8d2ad2b87aa2487dbb76d2605e0fa506b793048d6d4b516f25cbb4d9e0e3d/logo.gif",
                    "hero image": "/1536x800/5d8f7629cd78dffb465331a999d35309e34ebeff34946315c9f83d3f8e4d9c36/main.gif",
                    "default": "/160x30/c1f8d2ad2b87aa2487dbb76d2605e0fa506b793048d6d4b516f25cbb4d9e0e3d/logo.gif",
                    "large": "/170x32/c1f8d2ad2b87aa2487dbb76d2605e0fa506b793048d6d4b516f25cbb4d9e0e3d/logo.gif"
                }
            },
            "agencyId": "CPICHA",
            "email": "admin@fnrr.com.au"
        },
        "isSoldChannel": false,
        "isBuyChannel": false,
        "signatureProject": false,
        "agencyListingId": "2113328",
        "propertyFeatures": [
            {
                "features": [
                    "Balcony",
                    "Open Spaces: 1",
                    "Secure Parking",
                    "Swimming Pool - Inground"
                ],
                "section": "outdoor",
                "label": "Outdoor Features"
            },
            {
                "features": [
                    "Air Conditioning",
                    "Alarm System",
                    "Built-in Wardrobes",
                    "Intercom"
                ],
                "section": "indoor",
                "label": "Indoor Features"
            }
        ],
        "listingId": "436716888",
        "bond": { "display": "$3,400", "value": 3400 },
        "mainImage": {
            "server": "https://i3.au.reastatic.net",
            "name": "main photo",
            "uri": "/aa469ae0e542469a83179a2720dad6c903c907ca2c55b8a33e9e4fffbf95bff7/image.jpg"
        },
        "dateAvailable": {
            "date": "15 May 2023",
            "dateDisplay": "15 May 2023"
        },
        "modifiedDate": { "value": "" },
        "inspectionsAndAuctions": [],
        "generalFeatures": {
            "bedrooms": {
                "label": "Bedrooms: 2",
                "type": "bedrooms",
                "value": 2
            },
            "bathrooms": {
                "label": "Bathrooms: 2",
                "type": "bathrooms",
                "value": 2
            },
            "parkingSpaces": {
                "label": "Parking Spaces: 1",
                "type": "parkingSpaces",
                "value": 1
            }
        },
        "isRentChannel": true,
        "applyOnline": false
    },
    {
        "prettyUrl": "property-apartment-nsw-chatswood-436716344",
        "standard": false,
        "midtier": false,
        "lister": {
            "phoneNumber": "0419531656",
            "name": "Cassandra Burke",
            "mainPhoto": {
                "server": "https://i3.au.reastatic.net",
                "name": "main photo",
                "uri": "/a54d272a3e2a511371ca9e7291d7276ab70957a6a79398b959dd1bde28fac122/main.jpg"
            },
            "id": "3114536",
            "email": "chlc@mail.inspectrealestate.com.au"
        },
        "featured": false,
        "signature": true,
        "channel": "rent",
        "description": "This spacious top-floor apartment is located in the prestigious Sebel Residence. Boasting all the conveniences of Chatswood's city centre at your door, the apartment offers stylishly appointed interiors, resort-style amenities and open plan living flowing to a balcony with city views.<br/><br/>- Spacious bedrooms both with built-in robes<br/>- Open-plan living opens to a large balcony with a city view<br/>- Modern kitchen with gas cooking, internal laundry<br/>- Well-appointed bathroom with separate bath<br/>- Ducted A/C, intercom, lift access, secure parking<br/>- Swimming pool, gym, spa, sauna & 24hr concierge<br/>- Stroll to train station, buses & Westfield Shopping",
        "showAgencyLogo": true,
        "title": "Two-bedroom apartment in the heart of Chatswood",
        "listers": [
            {
                "phoneNumber": "0419531656",
                "name": "Cassandra Burke",
                "mainPhoto": {
                    "server": "https://i3.au.reastatic.net",
                    "name": "main photo",
                    "uri": "/a54d272a3e2a511371ca9e7291d7276ab70957a6a79398b959dd1bde28fac122/main.jpg"
                },
                "id": "3114536",
                "email": "chlc@mail.inspectrealestate.com.au"
            }
        ],
        "features": {
            "general": { "bedrooms": 2, "bathrooms": 2, "parkingSpaces": 1 }
        },
        "price": { "display": "$950 per week" },
        "propertyType": "apartment",
        "productDepth": "signature",
        "calculator": {
            "brandingColors": { "text": "#e4002b", "primary": "#ffffff" },
            "subtitle": "Calculate repayments for this property",
            "title": "Buy or Rent Calculator"
        },
        "images": [
            {
                "server": "https://i3.au.reastatic.net",
                "name": "photo",
                "uri": "/6585dbe28397ccebc359d6007f16f59e3f8900b52709e40be094e563f912bd1c/image.jpg"
            },
            {
                "server": "https://i3.au.reastatic.net",
                "name": "photo",
                "uri": "/8f282041b998f971d5b93fd0a1c88773837618329e542a9223c89e336ab124b7/image.jpg"
            },
            {
                "server": "https://i3.au.reastatic.net",
                "name": "photo",
                "uri": "/efecd65a5944b39dfe09671b506cbd0754fdf766e467595b88afc68fbe9ece73/image.jpg"
            },
            {
                "server": "https://i3.au.reastatic.net",
                "name": "photo",
                "uri": "/52d8d0de52a5ead3a5869e10657145cbab901698c5dd3903a2b80e9d99ab6e58/image.jpg"
            }
        ],
        "address": {
            "streetAddress": "1412/31-37 Victor Street",
            "locality": "Chatswood",
            "postcode": "2067",
            "suburb": "Chatswood",
            "location": { "latitude": -33.79757512, "longitude": 151.1821975 },
            "subdivisionCode": "NSW",
            "state": "NSW",
            "showAddress": true
        },
        "classicProject": false,
        "agency": {
            "address": {
                "streetAddress": "32 Burns Bay Road",
                "postcode": "2066",
                "suburb": "Lane Cove",
                "state": "NSW"
            },
            "phoneNumber": "02 9427 7466",
            "brandingColors": { "text": "#000000", "primary": "#ededbd" },
            "name": "CobdenHayson - Lane Cove",
            "logo": {
                "images": [
                    {
                        "server": "https://i3.au.reastatic.net",
                        "name": "large",
                        "uri": "/170x32/28c32b11cb94b84ebf376fe3f6f1db3b35ca0effe7725477e632dc28ccca7b52/logo.jpg"
                    },
                    {
                        "server": "https://i3.au.reastatic.net",
                        "name": "default",
                        "uri": "/160x30/28c32b11cb94b84ebf376fe3f6f1db3b35ca0effe7725477e632dc28ccca7b52/logo.jpg"
                    },
                    {
                        "server": "https://i3.au.reastatic.net",
                        "name": "small",
                        "uri": "/114x21/28c32b11cb94b84ebf376fe3f6f1db3b35ca0effe7725477e632dc28ccca7b52/logo.jpg"
                    },
                    {
                        "server": "https://i3.au.reastatic.net",
                        "name": "hero image",
                        "uri": "/1536x800/82d60bde08155d78c65301dfa897bf927ffd928011132f7cb8c7d909368d505f/main.jpg"
                    }
                ],
                "links": {
                    "small": "/114x21/28c32b11cb94b84ebf376fe3f6f1db3b35ca0effe7725477e632dc28ccca7b52/logo.jpg",
                    "hero image": "/1536x800/82d60bde08155d78c65301dfa897bf927ffd928011132f7cb8c7d909368d505f/main.jpg",
                    "default": "/160x30/28c32b11cb94b84ebf376fe3f6f1db3b35ca0effe7725477e632dc28ccca7b52/logo.jpg",
                    "large": "/170x32/28c32b11cb94b84ebf376fe3f6f1db3b35ca0effe7725477e632dc28ccca7b52/logo.jpg"
                }
            },
            "agencyId": "IKYJGO",
            "email": "yolanda@ch.com.au"
        },
        "isSoldChannel": false,
        "isBuyChannel": false,
        "signatureProject": false,
        "agencyListingId": "100P37148",
        "propertyFeatures": [
            {
                "features": ["Open Spaces: 1"],
                "section": "outdoor",
                "label": "Outdoor Features"
            },
            {
                "features": [
                    "Air Conditioning",
                    "Built-in Wardrobes",
                    "Ensuite: 1",
                    "Intercom"
                ],
                "section": "indoor",
                "label": "Indoor Features"
            }
        ],
        "listingId": "436716344",
        "bond": { "display": "$3,800", "value": 3800 },
        "mainImage": {
            "server": "https://i3.au.reastatic.net",
            "name": "main photo",
            "uri": "/8ae3da56737b902480374a98c75ddef5093db1ec8cffb8893ffe159e62d5f8e2/image.jpg"
        },
        "dateAvailable": {
            "date": "18 May 2023",
            "dateDisplay": "18 May 2023"
        },
        "modifiedDate": { "value": "" },
        "inspectionsAndAuctions": [],
        "generalFeatures": {
            "bedrooms": {
                "label": "Bedrooms: 2",
                "type": "bedrooms",
                "value": 2
            },
            "bathrooms": {
                "label": "Bathrooms: 2",
                "type": "bathrooms",
                "value": 2
            },
            "parkingSpaces": {
                "label": "Parking Spaces: 1",
                "type": "parkingSpaces",
                "value": 1
            }
        },
        "isRentChannel": true,
        "applyOnline": false
    }
]
